kz_iin_validator/__init__.py
kz_iin_validator/exceptions.py
kz_iin_validator/iin_extractor.py
kz_iin_validator/iin_generator.py
kz_iin_validator/iin_validator.py
kz_iin_validator/utils.py
kz_iin_validator-0.7.1.dist-info/LICENSE.txt
kz_iin_validator-0.7.1.dist-info/METADATA
kz_iin_validator-0.7.1.dist-info/WHEEL
kz_iin_validator-0.7.1.dist-info/top_level.txt
kz_iin_validator-0.7.1.dist-info/RECORD
