Metadata-Version: 2.1
Name: kz_iin_validator
Version: 0.7.1
Summary: Kazakhstan IIN parser and validator
Home-page: https://github.com/ZhymabekRoman/kz-iin-validator
Author: Zhymabek Roman
Author-email: robanokssamit@yandex.ru
License: MIT
Requires-Python: >=3.7
License-File: LICENSE.txt
